setup.py
Products/__init__.py
Products.ManagableIndex.egg-info/PKG-INFO
Products.ManagableIndex.egg-info/SOURCES.txt
Products.ManagableIndex.egg-info/dependency_links.txt
Products.ManagableIndex.egg-info/namespace_packages.txt
Products.ManagableIndex.egg-info/not-zip-safe
Products.ManagableIndex.egg-info/requires.txt
Products.ManagableIndex.egg-info/top_level.txt
Products/ManagableIndex/Evaluation.py
Products/ManagableIndex/FieldIndex.py
Products/ManagableIndex/KeywordIndex.py
Products/ManagableIndex/LICENSE.txt
Products/ManagableIndex/ManagableIndex.py
Products/ManagableIndex/PathIndex.py
Products/ManagableIndex/README.txt
Products/ManagableIndex/RangeIndex.py
Products/ManagableIndex/SimpleTextIndex.py
Products/ManagableIndex/Utils.py
Products/ManagableIndex/VERSION.txt
Products/ManagableIndex/ValueProvider.py
Products/ManagableIndex/WordIndex.py
Products/ManagableIndex/__init__.py
Products/ManagableIndex/configure.zcml
Products/ManagableIndex/exportimport.py
Products/ManagableIndex/fixPluginIndexes.py
Products/ManagableIndex/interfaces.py
Products/ManagableIndex/utf8.py
Products/ManagableIndex/doc/ManagableIndex.html
Products/ManagableIndex/tests/TestBase.py
Products/ManagableIndex/tests/__init__.py
Products/ManagableIndex/tests/test_ManagableIndex.py
Products/ManagableIndex/zpt/addForm.zpt