Metadata-Version: 1.0
Name: Products.ManagableIndex
Version: 2.1.4
Summary: Efficient flexible index construction framework with extended Field, Keyword, Path, Range indexes. For Zope 2.11 and above
Home-page: http://www.dieter.handshake.de/pyprojects/zope
Author: Dieter Maurer
Author-email: dieter@handshake.de
License: BSD (see "Products/ManagableIndex/LICENSE.txt", for details)
Keywords: Zope 2,index,framework,efficient,flexible
Platform: UNKNOWN
Classifier: Development Status :: 5 - Production/Stable
Classifier: Intended Audience :: Developers
Classifier: License :: OSI Approved :: BSD License
Classifier: Framework :: Zope2
Classifier: Operating System :: OS Independent
Classifier: Programming Language :: Python
Classifier: Topic :: Utilities
